x2y_metric/__init__.py
x2y_metric/metrics.py
x2y_metric-0.1.1.dist-info/METADATA
x2y_metric-0.1.1.dist-info/WHEEL
x2y_metric-0.1.1.dist-info/RECORD
