Metadata-Version: 2.4
Name: x2y-metric
Version: 0.1.1
Summary: Compute the X2Y metric for detecting relationships between variables
Author-email: Your Name <your.email@example.com>
License: MIT
Requires-Python: >=3.8
Requires-Dist: numpy>=1.23
Requires-Dist: pandas>=1.5
Requires-Dist: scikit-learn>=1.2
